adw/__init__.py
adw-0.1.1.dist-info/WHEEL
adw-0.1.1.dist-info/METADATA
adw-0.1.1.dist-info/RECORD
